README.md
setup.cfg
setup.py
assist/__init__.py
assist/vision/__init__.py
assist/vision/imagedatabunch.py
assist/vision/learner.py
assist/vision/main.py
assist/vision/utils.py
tf_assist.egg-info/PKG-INFO
tf_assist.egg-info/SOURCES.txt
tf_assist.egg-info/dependency_links.txt
tf_assist.egg-info/not-zip-safe
tf_assist.egg-info/requires.txt
tf_assist.egg-info/top_level.txt